ens/__init__.py
ens/abis.py
ens/auto.py
ens/constants.py
ens/contract_data.py
ens/exceptions.py
ens/main.py
ens/utils.py
veriteos_web3-4.7.1.post7.dist-info/METADATA
veriteos_web3-4.7.1.post7.dist-info/RECORD
veriteos_web3-4.7.1.post7.dist-info/WHEEL
veriteos_web3-4.7.1.post7.dist-info/top_level.txt
web3/__init__.py
web3/admin.py
web3/contract.py
web3/datastructures.py
web3/eth.py
web3/exceptions.py
web3/iban.py
web3/main.py
web3/manager.py
web3/miner.py
web3/module.py
web3/net.py
web3/parity.py
web3/personal.py
web3/pm.py
web3/shh.py
web3/testing.py
web3/txpool.py
web3/version.py
web3/auto/__init__.py
web3/auto/gethdev.py
web3/auto/http.py
web3/auto/infura.py
web3/auto/ipc.py
web3/auto/websocket.py
web3/gas_strategies/__init__.py
web3/gas_strategies/rpc.py
web3/gas_strategies/time_based.py
web3/middleware/__init__.py
web3/middleware/abi.py
web3/middleware/attrdict.py
web3/middleware/cache.py
web3/middleware/exception_handling.py
web3/middleware/exception_retry_request.py
web3/middleware/fixture.py
web3/middleware/formatting.py
web3/middleware/gas_price_strategy.py
web3/middleware/geth_poa.py
web3/middleware/names.py
web3/middleware/normalize_errors.py
web3/middleware/normalize_request_parameters.py
web3/middleware/pythonic.py
web3/middleware/signing.py
web3/middleware/simulate_unmined_transaction.py
web3/middleware/stalecheck.py
web3/middleware/validation.py
web3/providers/__init__.py
web3/providers/auto.py
web3/providers/base.py
web3/providers/ipc.py
web3/providers/rpc.py
web3/providers/tester.py
web3/providers/websocket.py
web3/providers/eth_tester/__init__.py
web3/providers/eth_tester/defaults.py
web3/providers/eth_tester/main.py
web3/providers/eth_tester/middleware.py
web3/utils/__init__.py
web3/utils/abi.py
web3/utils/blocks.py
web3/utils/caching.py
web3/utils/contracts.py
web3/utils/datatypes.py
web3/utils/decorators.py
web3/utils/empty.py
web3/utils/encoding.py
web3/utils/ens.py
web3/utils/events.py
web3/utils/filters.py
web3/utils/formatters.py
web3/utils/function_identifiers.py
web3/utils/http.py
web3/utils/hypothesis.py
web3/utils/math.py
